ssladapter/__init__.py
ssladapter/entry.py
ssladapter/ssl_adapter.py
ssladapter-0.1.3.dist-info/LICENSE
ssladapter-0.1.3.dist-info/METADATA
ssladapter-0.1.3.dist-info/WHEEL
ssladapter-0.1.3.dist-info/top_level.txt
ssladapter-0.1.3.dist-info/RECORD
