Metadata-Version: 2.1
Name: ssladapter
Version: 0.1.3
Summary: SSL Adapter for requests library
Home-page: https://github.com/lorenzofabro/ssladapter
Author: Lorenzo Fabro
Author-email: lorenzofabro1997@gmail.com
Requires-Python: >=3.6
License-File: LICENSE
Requires-Dist: requests ==2.27.1
